migflow-1.3.1.dist-info/AUTHORS.txt
migflow-1.3.1.dist-info/LICENSE.txt
migflow-1.3.1.dist-info/WHEEL
migflow-1.3.1.dist-info/COPYING.LESSER.txt
migflow-1.3.1.dist-info/top_level.txt
migflow-1.3.1.dist-info/METADATA
migflow-1.3.1.dist-info/COPYING.txt
migflow/abin.py
migflow/libmbfluid2.so
migflow/__init__.py
migflow/libgfortran.so.5
migflow/libscontact3.so
migflow/scipylsys.py
migflow/petsc4pylsys.py
migflow/libscontact2.so
migflow/libopenblas.so.0
migflow/_tools.py
migflow/libmbfluid3.so
migflow/free_surface.py
migflow/csr.py
migflow/fluid.py
migflow/time_integration.py
migflow/mumpslsys.py
migflow/scontact.py
migflow/petsclsys.py
migflow/lmgc90Interface.py
migflow/VTK.py
migflow/pardisolsys.py
migflow/libquadmath.so.0
migflow-1.3.1.data/data/share/doc/migflow/html/index.html
migflow-1.3.1.data/data/share/doc/migflow/html/py-modindex.html
migflow-1.3.1.data/data/share/doc/migflow/html/migflow.fluid.html
migflow-1.3.1.data/data/share/doc/migflow/html/.buildinfo
migflow-1.3.1.data/data/share/doc/migflow/html/examples.html
migflow-1.3.1.data/data/share/doc/migflow/html/objects.inv
migflow-1.3.1.data/data/share/doc/migflow/html/genindex.html
migflow-1.3.1.data/data/share/doc/migflow/html/migflow.time_integration.html
migflow-1.3.1.data/data/share/doc/migflow/html/main-features.html
migflow-1.3.1.data/data/share/doc/migflow/html/searchindex.js
migflow-1.3.1.data/data/share/doc/migflow/html/search.html
migflow-1.3.1.data/data/share/doc/migflow/html/migflow.html
migflow-1.3.1.data/data/share/doc/migflow/html/installation.html
migflow-1.3.1.data/data/share/doc/migflow/html/migflow.lmgc90Interface.html
migflow-1.3.1.data/data/share/doc/migflow/html/migflow.scontact.html
migflow-1.3.1.data/data/share/doc/migflow/html/_sources/migflow.fluid.rst.txt
migflow-1.3.1.data/data/share/doc/migflow/html/_sources/migflow.time_integration.rst.txt
migflow-1.3.1.data/data/share/doc/migflow/html/_sources/installation.rst.txt
migflow-1.3.1.data/data/share/doc/migflow/html/_sources/index.rst.txt
migflow-1.3.1.data/data/share/doc/migflow/html/_sources/migflow.scontact.rst.txt
migflow-1.3.1.data/data/share/doc/migflow/html/_sources/main-features.rst.txt
migflow-1.3.1.data/data/share/doc/migflow/html/_sources/examples.rst.txt
/tmp/tmpzkuhrv07/migflow-1.3.1.dist-info/RECORD
