Metadata-Version: 2.1
Name: migflow
Version: 1.3
Summary: Model for Immersed Granular Flows
Home-page: https://www.migflow.be
Author: Migflow Team
Author-email: jonathan.lambrechts@uclouvain.be
License: GPLv3
Platform: Posix
Platform: Windows
Classifier: Environment :: Console
Classifier: Development Status :: 4 - Beta
Classifier: License :: OSI Approved :: GNU General Public License v3 (GPLv3)
Classifier: Operating System :: POSIX :: Linux
Classifier: Operating System :: Microsoft :: Windows
Classifier: Operating System :: MacOS :: MacOS X
Classifier: Programming Language :: C
Classifier: Programming Language :: Python
Classifier: Topic :: Scientific/Engineering
Requires-Python: >=3.6
Requires-Dist: scipy
